mocksey/__init__.py
mocksey/mocksey.py
mocksey/tests/__init__.py
mocksey/tests/test_run_asserts.py
mocksey/tests/test_simple_mock.py
mocksey/tests/test_tweaksey_tweak_mock.py
mocksey/tweaksey.py
mocksey-0.4.0.dist-info/LICENSE
mocksey-0.4.0.dist-info/WHEEL
mocksey-0.4.0.dist-info/METADATA
mocksey-0.4.0.dist-info/RECORD
