Metadata-Version: 2.1
Name: mocksey
Version: 0.4.0
Summary: Stupidly-simple python mocking utility with moxie.
Home-page: https://github.com/mitgr81/mocksey
License: MIT
Author: Chris McGraw
Author-email: mitgr81+mocksey@mitgr81.com
Requires-Python: >=3.9,<4.0
Classifier: Development Status :: 4 - Beta
Classifier: Intended Audience :: Developers
Classifier: License :: OSI Approved :: MIT License
Classifier: Natural Language :: English
Classifier: Operating System :: OS Independent
Classifier: Programming Language :: Python :: 3
Classifier: Programming Language :: Python :: 3.9
Classifier: Topic :: Software Development :: Testing
Project-URL: Repository, https://github.com/mitgr81/mocksey
